num2words/__init__.py
num2words/num2words.py
utils/__init__.py
utils/small_function.py
persian_num2words-1.3.dist-info/LICENSE.txt
persian_num2words-1.3.dist-info/METADATA
persian_num2words-1.3.dist-info/WHEEL
persian_num2words-1.3.dist-info/top_level.txt
persian_num2words-1.3.dist-info/RECORD
