Metadata-Version: 2.1
Name: persian_num2words
Version: 1.3
Summary: A Package to Convert Numbers to Words in Persian.
Home-page: https://github.com/mosihere/persian_num2words
Author: Mosihere
Author-email: mosihere@gmail.com
Project-URL: Bug Tracker, https://github.com/mosihere/persian_num2words/issues
Project-URL: repository, https://github.com/mosihere/persian_num2words
Classifier: Programming Language :: Python :: 3
Classifier: License :: OSI Approved :: MIT License
Classifier: Operating System :: OS Independent
Requires-Python: >=3.6
License-File: LICENSE.txt
